{"url":"https://www.alleangeln.de/gewaesser/parkteich-dardesheim","slug":"parkteich-dardesheim","id":"parkteich-dardesheim","name":"Parkteich Dardesheim","description":"Parkteich Dardesheim ist ein Teich in Sachsen-Anhalt in der Nähe von Osterwieck. Das Gewässer wird von unseren Mitgliedern relativ stark befischt und als Top Gewässer bewertet.","followers":19,"catches_count":31,"images_count":0,"most_caught_fish":["Karpfen","Giebel","Brachse","Flussbarsch","Rotfeder"],"best_method":"Grundangeln","breadcrumbs":[],"fish":[],"water_type":"Teich","lat":51.976297953337,"lng":10.833184383809,"geocode_source":"alleangeln_json_ld","country":"DE","last_updated":"2026-05-07T11:10:25.312Z","source":"alle-angeln","source_platform":"alleangeln","global_id":"alleangeln-parkteich-dardesheim","external_ids":{"alleangeln":"parkteich-dardesheim"}}