{"url":"https://www.alleangeln.de/gewaesser/restloch-1-a-kittlitz","slug":"restloch-1-a-kittlitz","id":"restloch-1-a-kittlitz","name":"Restloch 1 A (Kittlitz)","description":"Restloch 1 A (Kittlitz) ist ein Baggersee in Brandenburg in der Nähe von Lübbenau/Spreewald. Das Gewässer wird von unseren Mitgliedern sehr stark befischt und als Top Gewässer bewertet.","followers":288,"catches_count":56,"images_count":9,"most_caught_fish":["Flussbarsch","Hecht","Brachse","Karpfen","Rotfeder","Schleie","Rotauge","Graskarpfen"],"best_method":"Posenfischen","breadcrumbs":[],"fish":[],"water_type":"Baggersee","lat":51.829505542483,"lng":13.934333324432,"geocode_source":"alleangeln_json_ld","country":"DE","last_updated":"2026-05-07T11:22:38.062Z","source":"alle-angeln","source_platform":"alleangeln","global_id":"alleangeln-restloch-1-a-kittlitz","external_ids":{"alleangeln":"restloch-1-a-kittlitz"}}