{"id":"alleangeln-deichsee-buga-see-düsseldorf","source_platform":"alleangeln","source_ids":{"alleangeln":"deichsee-buga-see-düsseldorf"},"name":"Deichsee (Buga-See Düsseldorf)","water_type":"Baggersee","country":"DE","center":{"lat":51.196593,"lng":6.808007,"source":"alleangeln_json_ld","confidence":"medium"},"geometry":{"points":[{"lat":51.196593,"lng":6.808007}],"lines":[],"polygons":[],"source":"alleangeln_json_ld","confidence":"low"},"links":{"source":"https://www.alleangeln.de/gewaesser/deichsee-buga-see-düsseldorf","hejfish":null,"alleangeln":"https://www.alleangeln.de/gewaesser/deichsee-buga-see-düsseldorf","image":null},"fish":["Flussbarsch","Hecht","Schleie","Sonnenbarsch","Karpfen","Aal","Brachse","Rotfeder"],"metadata":{"platform":"alleangeln","geocode_source":"alleangeln_json_ld","slug":"deichsee-buga-see-düsseldorf","description":"Deichsee (Buga-See Düsseldorf) ist ein Baggersee in Nordrhein-Westfalen in der Nähe von Düsseldorf. Das Gewässer wird von unseren Mitgliedern sehr stark befischt und als Top Gewässer bewertet.","followers":271,"catches_count":52,"images_count":4,"best_method":"Spinnfischen","source_last_updated":"2026-05-07T11:21:12.115Z","error":false},"last_updated":"2026-05-07T11:21:12.115Z"}