{"id":"alleangeln-mittelkaempesee","source_platform":"alleangeln","source_ids":{"alleangeln":"mittelkaempesee"},"name":"Mittelkämpesee","water_type":"See","country":"DE","center":{"lat":53.110758,"lng":8.900506,"source":"alleangeln_json_ld","confidence":"medium"},"geometry":{"points":[{"lat":53.110758,"lng":8.900506}],"lines":[],"polygons":[],"source":"alleangeln_json_ld","confidence":"low"},"links":{"source":"https://www.alleangeln.de/gewaesser/mittelkaempesee","hejfish":null,"alleangeln":"https://www.alleangeln.de/gewaesser/mittelkaempesee","image":null},"fish":["Karpfen","Rotauge","Flussbarsch"],"metadata":{"platform":"alleangeln","geocode_source":"alleangeln_json_ld","slug":"mittelkaempesee","description":"Mittelkämpesee ist ein See in Bremen. Das Gewässer wird von unseren Mitgliedern relativ wenig befischt und als Top Angelreview bewertet.","followers":31,"catches_count":14,"images_count":0,"best_method":"Posenfischen","source_last_updated":"2026-05-07T10:50:31.185Z","error":false},"last_updated":"2026-05-07T10:50:31.185Z"}