{"id":"alleangeln-neckar-ladenburg","source_platform":"alleangeln","source_ids":{"alleangeln":"neckar-ladenburg"},"name":"Neckar (Ladenburg)","water_type":"Fluss","country":"DE","center":{"lat":49.471882,"lng":8.59918,"source":"alleangeln_json_ld","confidence":"medium"},"geometry":{"points":[{"lat":49.471882,"lng":8.59918}],"lines":[],"polygons":[],"source":"alleangeln_json_ld","confidence":"low"},"links":{"source":"https://www.alleangeln.de/gewaesser/neckar-ladenburg","hejfish":null,"alleangeln":"https://www.alleangeln.de/gewaesser/neckar-ladenburg","image":null},"fish":["Wels","Flussbarsch","Rapfen","Zander","Döbel","6 weitere Fischarten"],"metadata":{"platform":"alleangeln","geocode_source":"alleangeln_json_ld","slug":"neckar-ladenburg","description":"Neckar (Ladenburg) ist ein Fluss in Baden-Württemberg in der Nähe von Ladenburg. Das Gewässer wird von unseren Mitgliedern sehr stark befischt und als gutes Gewässer bewertet.","followers":65,"catches_count":85,"images_count":7,"best_method":"Spinnfischen","source_last_updated":"2026-05-07T11:29:53.452Z","error":false},"last_updated":"2026-05-07T11:29:53.452Z"}