{"url":"https://www.alleangeln.de/gewaesser/westerender-ehe","slug":"westerender-ehe","id":"westerender-ehe","name":"Westerender Ehe","description":"Westerender Ehe ist ein Kanal in Niedersachsen in der Nähe von Südbrookmerland. Das Gewässer wird von unseren Mitgliedern sehr stark befischt und als Top Gewässer bewertet.","followers":166,"catches_count":66,"images_count":8,"most_caught_fish":["Hecht","Brachse","Flussbarsch","Schleie","Aal","4 weitere Fischarten"],"best_method":"Posenfischen","breadcrumbs":[],"fish":[],"water_type":"Kanal","lat":53.411789555277,"lng":7.3006441666565,"geocode_source":"alleangeln_json_ld","country":"DE","last_updated":"2026-05-07T11:25:35.693Z","source":"alle-angeln","source_platform":"alleangeln","global_id":"alleangeln-westerender-ehe","external_ids":{"alleangeln":"westerender-ehe"}}