{"id":"alleangeln-kerteminde-fjord","source_platform":"alleangeln","source_ids":{"alleangeln":"kerteminde-fjord"},"name":"Kerteminde Fjord","water_type":"Fjord","country":"DE","center":{"lat":55.44851,"lng":10.567459,"source":"alleangeln_json_ld","confidence":"medium"},"geometry":{"points":[{"lat":55.44851,"lng":10.567459}],"lines":[],"polygons":[],"source":"alleangeln_json_ld","confidence":"low"},"links":{"source":"https://www.alleangeln.de/gewaesser/kerteminde-fjord","hejfish":null,"alleangeln":"https://www.alleangeln.de/gewaesser/kerteminde-fjord","image":null},"fish":["Meerforelle","Bachforelle","Flunder","Petermännchen","Aal","9 weitere Fischarten"],"metadata":{"platform":"alleangeln","geocode_source":"alleangeln_json_ld","slug":"kerteminde-fjord","description":"Kerteminde Fjord ist ein Fjord in Dänemark. Das Gewässer wird von unseren Mitgliedern relativ stark befischt und als Top Gewässer bewertet.","followers":45,"catches_count":21,"images_count":0,"best_method":"Spinnfischen","source_last_updated":"2026-05-07T11:00:27.559Z","error":false},"last_updated":"2026-05-07T11:00:27.559Z"}