{"url":"https://www.alleangeln.de/gewaesser/muehlpleisse-leipzig","slug":"muehlpleisse-leipzig","id":"muehlpleisse-leipzig","name":"Mühlpleiße (Leipzig)","description":"Mühlpleiße (Leipzig) ist ein Fluss in Sachsen in der Nähe von Leipzig. Das Gewässer wird von unseren Mitgliedern relativ wenig befischt und als Top Angelreview bewertet.","followers":59,"catches_count":18,"images_count":6,"most_caught_fish":["Döbel","Barbe","Rotauge","Rotfeder"],"best_method":"Freie Leine","breadcrumbs":[],"fish":[],"water_type":"Fluss","lat":51.296728508654,"lng":12.379082255065,"geocode_source":"alleangeln_json_ld","country":"DE","last_updated":"2026-05-07T10:57:06.304Z","source":"alle-angeln","source_platform":"alleangeln","global_id":"alleangeln-muehlpleisse-leipzig","external_ids":{"alleangeln":"muehlpleisse-leipzig"}}