{"url":"https://www.alleangeln.de/gewaesser/lander-bach-verl","slug":"lander-bach-verl","id":"lander-bach-verl","name":"Lander Bach (Verl)","description":"Lander Bach (Verl) ist ein Bach in Nordrhein-Westfalen in der Nähe von Verl. Das Gewässer wird von unseren Mitgliedern sehr wenig befischt und als Top Gewässer bewertet.","followers":22,"catches_count":20,"images_count":0,"most_caught_fish":["Rotauge","Bachforelle"],"best_method":"Posenfischen","breadcrumbs":[],"fish":[],"water_type":"Bach","lat":51.889755964828,"lng":8.5275042057037,"geocode_source":"alleangeln_json_ld","country":"DE","last_updated":"2026-05-07T10:59:17.834Z","source":"alle-angeln","source_platform":"alleangeln","global_id":"alleangeln-lander-bach-verl","external_ids":{"alleangeln":"lander-bach-verl"}}