{"id":"alleangeln-gondelteich-marienberg","source_platform":"alleangeln","source_ids":{"alleangeln":"gondelteich-marienberg"},"name":"Gondelteich (Marienberg)","water_type":"See","country":"DE","center":{"lat":50.650434,"lng":13.143269,"source":"alleangeln_json_ld","confidence":"medium"},"geometry":{"points":[{"lat":50.650434,"lng":13.143269}],"lines":[],"polygons":[],"source":"alleangeln_json_ld","confidence":"low"},"links":{"source":"https://www.alleangeln.de/gewaesser/gondelteich-marienberg","hejfish":null,"alleangeln":"https://www.alleangeln.de/gewaesser/gondelteich-marienberg","website":"http://www.angelatlas-sachsen.de/#C02-101","image":null},"fish":["Karpfen","Hecht","Rotauge","Brachse","Flussbarsch","5 weitere Fischarten"],"metadata":{"platform":"alleangeln","geocode_source":"alleangeln_json_ld","slug":"gondelteich-marienberg","description":"Gondelteich (Marienberg) ist ein See in Sachsen in der Nähe von Marienberg. Das Gewässer wird von unseren Mitgliedern sehr stark befischt und als Top Gewässer bewertet.","followers":251,"catches_count":130,"images_count":13,"website":"http://www.angelatlas-sachsen.de/#C02-101","best_method":"Posenfischen","scraper_version":2,"source_last_updated":"2026-05-11T20:00:28.443Z","error":false},"last_updated":"2026-05-11T20:00:28.443Z"}