{"id":"alleangeln-siedewitzstau-thallwitz","source_platform":"alleangeln","source_ids":{"alleangeln":"siedewitzstau-thallwitz"},"name":"Siedewitzstau (Thallwitz)","water_type":"Weiher","country":"DE","center":{"lat":51.425805,"lng":12.699813,"source":"alleangeln_json_ld","confidence":"medium"},"geometry":{"points":[{"lat":51.425805,"lng":12.699813}],"lines":[],"polygons":[],"source":"alleangeln_json_ld","confidence":"low"},"links":{"source":"https://www.alleangeln.de/gewaesser/siedewitzstau-thallwitz","hejfish":null,"alleangeln":"https://www.alleangeln.de/gewaesser/siedewitzstau-thallwitz","website":"http://www.angelatlas-sachsen.de/#L08-108","image":null},"fish":["Karpfen","Hecht","Flussbarsch","Schleie","Giebel","3 weitere Fischarten","Graskarpfen","Aal","Güster"],"metadata":{"platform":"alleangeln","geocode_source":"alleangeln_json_ld","slug":"siedewitzstau-thallwitz","description":"Siedewitzstau (Thallwitz) ist ein Weiher in Sachsen in der Nähe von Thallwitz. Das Gewässer wird von unseren Mitgliedern sehr stark befischt und als Top Gewässer bewertet.","followers":171,"catches_count":128,"images_count":5,"website":"http://www.angelatlas-sachsen.de/#L08-108","best_method":"Feedern","scraper_version":2,"source_last_updated":"2026-05-11T20:00:06.160Z","error":false},"last_updated":"2026-05-11T20:00:06.160Z"}