{"url":"https://www.alleangeln.de/gewaesser/illerkanal-kirchdorf-iller","slug":"illerkanal-kirchdorf-iller","id":"illerkanal-kirchdorf-iller","name":"Illerkanal (Kirchdorf/Iller)","description":"Illerkanal (Kirchdorf/Iller) ist ein Fluss in Baden-Württemberg in der Nähe von Kirchdorf an der Iller. Das Gewässer wird von unseren Mitgliedern sehr stark befischt und als gutes Gewässer bewertet.","followers":488,"catches_count":103,"images_count":4,"most_caught_fish":["Regenbogenforelle","Bachforelle","Barbe","Flussbarsch","Hecht","4 weitere Fischarten"],"best_method":"Spinnfischen","breadcrumbs":[],"fish":[],"water_type":"Fluss","lat":48.055635500668,"lng":10.121035344082,"geocode_source":"alleangeln_json_ld","country":"DE","last_updated":"2026-05-07T11:32:33.074Z","source":"alle-angeln","source_platform":"alleangeln","global_id":"alleangeln-illerkanal-kirchdorf-iller","external_ids":{"alleangeln":"illerkanal-kirchdorf-iller"}}