{"url":"https://www.alleangeln.de/gewaesser/mühlteich-dieskau","slug":"mühlteich-dieskau","id":"mühlteich-dieskau","name":"Mühlteich (Dieskau)","description":"Mühlteich (Dieskau) ist ein Teich in Sachsen-Anhalt in der Nähe von Kabelsketal. Das Gewässer wird von unseren Mitgliedern relativ stark befischt und als Top Gewässer bewertet.","followers":87,"catches_count":35,"images_count":4,"most_caught_fish":["Karpfen","Hecht","Aal","Karausche","Giebel"],"best_method":"Grundangeln","breadcrumbs":[],"fish":[],"water_type":"Teich","lat":51.430699574284,"lng":12.030567796295,"geocode_source":"alleangeln_json_ld","country":"DE","last_updated":"2026-05-07T11:12:40.755Z","source":"alle-angeln","source_platform":"alleangeln","global_id":"alleangeln-mühlteich-dieskau","external_ids":{"alleangeln":"mühlteich-dieskau"}}