{"id":"alleangeln-ostsee-fehmarn-strukkamp","source_platform":"alleangeln","source_ids":{"alleangeln":"ostsee-fehmarn-strukkamp"},"name":"Ostsee (Fehmarn-Strukkamp)","water_type":"Küste","country":"DE","center":{"lat":54.411913,"lng":11.095515,"source":"alleangeln_json_ld","confidence":"medium"},"geometry":{"points":[{"lat":54.411913,"lng":11.095515}],"lines":[],"polygons":[],"source":"alleangeln_json_ld","confidence":"low"},"links":{"source":"https://www.alleangeln.de/gewaesser/ostsee-fehmarn-strukkamp","hejfish":null,"alleangeln":"https://www.alleangeln.de/gewaesser/ostsee-fehmarn-strukkamp","website":"http://www.fehmarn.de/de/fehmarn/aktiv_erkunden_im_meer_aktiv/angeln.php","image":null},"fish":["Hornhecht","Meerforelle","Scholle","Flunder","Dorsch","1 weitere Fischarten","Kliesche"],"metadata":{"platform":"alleangeln","geocode_source":"alleangeln_json_ld","slug":"ostsee-fehmarn-strukkamp","description":"Ostsee (Fehmarn-Strukkamp) ist ein Küstengewässer in Schleswig-Holstein in der Nähe von Fehmarn. Das Gewässer wird von unseren Mitgliedern sehr stark befischt und als Top Gewässer bewertet.","followers":610,"catches_count":66,"images_count":10,"website":"http://www.fehmarn.de/de/fehmarn/aktiv_erkunden_im_meer_aktiv/angeln.php","best_method":"Meeresangeln (Küste)","scraper_version":2,"source_last_updated":"2026-05-11T19:49:51.280Z","error":false},"last_updated":"2026-05-11T19:49:51.280Z"}