{"url":"https://www.alleangeln.de/gewaesser/ziegelkampsee-hemmoor","slug":"ziegelkampsee-hemmoor","id":"ziegelkampsee-hemmoor","name":"Ziegelkampsee (Hemmoor)","description":"Ziegelkampsee (Hemmoor) ist ein See in Niedersachsen in der Nähe von Hemmoor. Das Gewässer wird von unseren Mitgliedern relativ wenig befischt und als Top Angelreview bewertet.","followers":68,"catches_count":18,"images_count":1,"most_caught_fish":["Brachse","Flussbarsch","Karpfen","Schleie","Hecht","Rotauge"],"best_method":"Grundangeln","breadcrumbs":[],"fish":[],"water_type":"See","lat":53.682144583,"lng":9.1653371689999,"geocode_source":"alleangeln_json_ld","country":"DE","last_updated":"2026-05-07T10:56:10.211Z","source":"alle-angeln","source_platform":"alleangeln","global_id":"alleangeln-ziegelkampsee-hemmoor","external_ids":{"alleangeln":"ziegelkampsee-hemmoor"}}