{"id":"alleangeln-tauber-lauda-königshofen","source_platform":"alleangeln","source_ids":{"alleangeln":"tauber-lauda-königshofen"},"name":"Tauber (Lauda-Königshofen)","water_type":"Fluss","country":"DE","center":{"lat":49.564805,"lng":9.712451,"source":"alleangeln_json_ld","confidence":"medium"},"geometry":{"points":[{"lat":49.564805,"lng":9.712451}],"lines":[],"polygons":[],"source":"alleangeln_json_ld","confidence":"low"},"links":{"source":"https://www.alleangeln.de/gewaesser/tauber-lauda-königshofen","hejfish":null,"alleangeln":"https://www.alleangeln.de/gewaesser/tauber-lauda-königshofen","website":"http://www.asv-lauda.de/","image":null},"fish":["Rotauge","Gründling","Flussbarsch","Döbel","Nase","13 weitere Fischarten"],"metadata":{"platform":"alleangeln","geocode_source":"alleangeln_json_ld","slug":"tauber-lauda-königshofen","description":"Tauber (Lauda-Königshofen) ist ein Fluss in Baden-Württemberg in der Nähe von Lauda-Königshofen. Das Gewässer wird von unseren Mitgliedern sehr stark befischt und als Top Gewässer bewertet.","followers":283,"catches_count":406,"images_count":4,"website":"http://www.asv-lauda.de/","best_method":"Grundangeln","scraper_version":2,"source_last_updated":"2026-05-11T20:08:36.869Z","error":false},"last_updated":"2026-05-11T20:08:36.869Z"}