{"id":"alleangeln-teich-des-asv-kleebachtal-dornholzhausen","source_platform":"alleangeln","source_ids":{"alleangeln":"teich-des-asv-kleebachtal-dornholzhausen"},"name":"Teich des ASV Kleebachtal (Dornholzhausen)","water_type":"Teich","country":"DE","center":{"lat":50.491235,"lng":8.581917,"source":"alleangeln_json_ld","confidence":"medium"},"geometry":{"points":[{"lat":50.491235,"lng":8.581917}],"lines":[],"polygons":[],"source":"alleangeln_json_ld","confidence":"low"},"links":{"source":"https://www.alleangeln.de/gewaesser/teich-des-asv-kleebachtal-dornholzhausen","hejfish":null,"alleangeln":"https://www.alleangeln.de/gewaesser/teich-des-asv-kleebachtal-dornholzhausen","image":null},"fish":["Regenbogenforelle","Schleie"],"metadata":{"platform":"alleangeln","geocode_source":"alleangeln_json_ld","slug":"teich-des-asv-kleebachtal-dornholzhausen","description":"Teich des ASV Kleebachtal (Dornholzhausen) ist ein Teich in Hessen in der Nähe von Langgöns. Das Gewässer wird von unseren Mitgliedern sehr wenig befischt und als Top Gewässer bewertet.","followers":7,"catches_count":7,"images_count":0,"best_method":"Posenfischen","source_last_updated":"2026-05-07T10:17:51.951Z","error":false},"last_updated":"2026-05-07T10:17:51.951Z"}