{"url":"https://www.alleangeln.de/gewaesser/brack-4-buxtehude","slug":"brack-4-buxtehude","id":"brack-4-buxtehude","name":"Brack 4 (Buxtehude)","description":"Brack 4 (Buxtehude) ist ein Teich in Niedersachsen in der Nähe von Buxtehude. Das Gewässer wird von unseren Mitgliedern relativ wenig befischt und als Top Angelreview bewertet.","followers":69,"catches_count":12,"images_count":0,"most_caught_fish":["Karpfen","Hecht","Flussbarsch","Kaulbarsch"],"best_method":"Grundangeln","breadcrumbs":[],"fish":[],"water_type":"Teich","lat":53.485752544085,"lng":9.7099528313993,"geocode_source":"alleangeln_json_ld","country":"DE","last_updated":"2026-05-07T10:45:40.033Z","source":"alle-angeln","source_platform":"alleangeln","global_id":"alleangeln-brack-4-buxtehude","external_ids":{"alleangeln":"brack-4-buxtehude"}}