{"id":"alleangeln-mellnitz-üselitzer-wiek","source_platform":"alleangeln","source_ids":{"alleangeln":"mellnitz-üselitzer-wiek"},"name":"Mellnitz-Üselitzer Wiek","water_type":"See","country":"DE","center":{"lat":54.268256,"lng":13.305149,"source":"alleangeln_json_ld","confidence":"medium"},"geometry":{"points":[{"lat":54.268256,"lng":13.305149}],"lines":[],"polygons":[],"source":"alleangeln_json_ld","confidence":"low"},"links":{"source":"https://www.alleangeln.de/gewaesser/mellnitz-üselitzer-wiek","hejfish":null,"alleangeln":"https://www.alleangeln.de/gewaesser/mellnitz-üselitzer-wiek","image":null},"fish":["Hecht","Flussbarsch","Rotfeder"],"metadata":{"platform":"alleangeln","geocode_source":"alleangeln_json_ld","slug":"mellnitz-üselitzer-wiek","description":"Mellnitz-Üselitzer Wiek ist ein See in Mecklenburg-Vorpommern in der Nähe von Poseritz. Das Gewässer wird von unseren Mitgliedern relativ stark befischt und als Top Gewässer bewertet.","followers":91,"catches_count":24,"images_count":1,"best_method":"Spinnfischen","source_last_updated":"2026-05-07T11:04:25.419Z","error":false},"last_updated":"2026-05-07T11:04:25.419Z"}