{"url":"https://www.alleangeln.de/gewaesser/fuhne-radegast","slug":"fuhne-radegast","id":"fuhne-radegast","name":"Fuhne (Radegast)","description":"Fuhne (Radegast) ist ein Fluss in Sachsen-Anhalt in der Nähe von Südliches Anhalt. Das Gewässer wird von unseren Mitgliedern relativ stark befischt und als gutes Gewässer bewertet.","followers":24,"catches_count":23,"images_count":0,"most_caught_fish":["Hecht","Karpfen","Flussbarsch","Graskarpfen"],"best_method":"Spinnfischen","breadcrumbs":[],"fish":[],"water_type":"Fluss","lat":51.649058733983,"lng":12.09685921669,"geocode_source":"alleangeln_json_ld","country":"DE","last_updated":"2026-05-07T11:03:24.066Z","source":"alle-angeln","source_platform":"alleangeln","global_id":"alleangeln-fuhne-radegast","external_ids":{"alleangeln":"fuhne-radegast"}}