{"url":"https://www.alleangeln.de/gewaesser/nordsee-nordstrand","slug":"nordsee-nordstrand","id":"nordsee-nordstrand","name":"Nordsee (Nordstrand)","description":"Nordsee (Nordstrand) ist ein Küstengewässer in Schleswig-Holstein. Das Gewässer wird von unseren Mitgliedern relativ stark befischt und als Top Gewässer bewertet.","followers":480,"catches_count":48,"images_count":0,"most_caught_fish":["Dorsch","Wolfsbarsch","Makrele","Hering","Hornhecht","7 weitere Fischarten"],"best_method":"Meeresangeln (Küste)","breadcrumbs":[],"fish":[],"water_type":"Küstengewässer","lat":54.498816829,"lng":8.806310445,"geocode_source":"alleangeln_json_ld","country":"DE","last_updated":"2026-05-07T11:19:35.314Z","source":"alle-angeln","source_platform":"alleangeln","global_id":"alleangeln-nordsee-nordstrand","external_ids":{"alleangeln":"nordsee-nordstrand"}}