{"url":"https://www.alleangeln.de/gewaesser/barschteich-rückersdorf","slug":"barschteich-rückersdorf","id":"barschteich-rückersdorf","name":"Barschteich (Rückersdorf)","description":"Barschteich (Rückersdorf) ist ein Teich in Brandenburg in der Nähe von Rückersdorf. Das Gewässer wird von unseren Mitgliedern sehr wenig befischt und als Top Gewässer bewertet.","followers":136,"catches_count":9,"images_count":0,"most_caught_fish":["Karpfen","Zwergwels","Flussbarsch","Sonnenbarsch"],"best_method":"Posenfischen","breadcrumbs":[],"fish":[],"water_type":"Teich","lat":51.591333327334,"lng":13.586780058861,"geocode_source":"alleangeln_json_ld","country":"DE","last_updated":"2026-05-07T10:22:16.897Z","source":"alle-angeln","source_platform":"alleangeln","global_id":"alleangeln-barschteich-rückersdorf","external_ids":{"alleangeln":"barschteich-rückersdorf"}}