{"url":"https://www.alleangeln.de/gewaesser/speicherbecken-rachlau","slug":"speicherbecken-rachlau","id":"speicherbecken-rachlau","name":"Speicherbecken Rachlau","description":"Speicherbecken Rachlau ist ein Stausee in Sachsen in der Nähe von Kubschütz. Das Gewässer wird von unseren Mitgliedern sehr stark befischt und als Top Gewässer bewertet.","followers":612,"catches_count":223,"images_count":25,"most_caught_fish":["Karpfen","Flussbarsch","Hecht","Rotauge","Brachse","8 weitere Fischarten"],"best_method":"Grundangeln","breadcrumbs":[],"fish":[],"water_type":"Stausee","lat":51.134980742823,"lng":14.50155435582,"geocode_source":"alleangeln_json_ld","country":"DE","last_updated":"2026-05-07T11:40:25.752Z","source":"alle-angeln","source_platform":"alleangeln","global_id":"alleangeln-speicherbecken-rachlau","external_ids":{"alleangeln":"speicherbecken-rachlau"}}