{"id":"alleangeln-kinzig-langenselbold","source_platform":"alleangeln","source_ids":{"alleangeln":"kinzig-langenselbold"},"name":"Kinzig (Langenselbold)","water_type":"Fluss","country":"DE","center":{"lat":50.165277,"lng":9.045755,"source":"alleangeln_json_ld","confidence":"medium"},"geometry":{"points":[{"lat":50.165277,"lng":9.045755}],"lines":[],"polygons":[],"source":"alleangeln_json_ld","confidence":"low"},"links":{"source":"https://www.alleangeln.de/gewaesser/kinzig-langenselbold","hejfish":null,"alleangeln":"https://www.alleangeln.de/gewaesser/kinzig-langenselbold","website":"http://www.ig-kinzig.de/","image":null},"fish":["Bachforelle","Döbel","Barbe","Wels","Flussbarsch"],"metadata":{"platform":"alleangeln","geocode_source":"alleangeln_json_ld","slug":"kinzig-langenselbold","description":"Kinzig (Langenselbold) ist ein Fluss in Hessen in der Nähe von Langenselbold. Das Gewässer wird von unseren Mitgliedern relativ wenig befischt und als gutes Angelreview bewertet.","followers":178,"catches_count":15,"images_count":2,"website":"http://www.ig-kinzig.de/","best_method":"Spinnfischen","scraper_version":2,"source_last_updated":"2026-05-11T19:11:08.844Z","error":false},"last_updated":"2026-05-11T19:11:08.844Z"}