{"url":"https://www.alleangeln.de/gewaesser/lippe-lippborg","slug":"lippe-lippborg","id":"lippe-lippborg","name":"Lippe (Lippborg)","description":"Lippe (Lippborg) ist ein Fluss in Nordrhein-Westfalen in der Nähe von Lippetal. Das Gewässer wird von unseren Mitgliedern sehr stark befischt und als Top Gewässer bewertet.","followers":792,"catches_count":163,"images_count":7,"most_caught_fish":["Flussbarsch","Karpfen","Hecht","Aal","Döbel","10 weitere Fischarten"],"best_method":"Grundangeln","breadcrumbs":[],"fish":[],"water_type":"Fluss","lat":51.664057654561,"lng":8.0341514440171,"geocode_source":"alleangeln_json_ld","country":"DE","last_updated":"2026-05-07T11:38:01.516Z","source":"alle-angeln","source_platform":"alleangeln","global_id":"alleangeln-lippe-lippborg","external_ids":{"alleangeln":"lippe-lippborg"}}