{"url":"https://www.alleangeln.de/gewaesser/ludwigsteich-roßdorf","slug":"ludwigsteich-roßdorf","id":"ludwigsteich-roßdorf","name":"Ludwigsteich (Roßdorf)","description":"Ludwigsteich (Roßdorf) ist ein Teich in Hessen in der Nähe von Roßdorf. Das Gewässer wird von unseren Mitgliedern relativ stark befischt und als Top Gewässer bewertet.","followers":63,"catches_count":47,"images_count":1,"most_caught_fish":["Karpfen","Regenbogenforelle","Zander","Aal","Graskarpfen","Flussbarsch","Rotauge","Rotfeder"],"best_method":"Grundangeln","breadcrumbs":[],"fish":[],"water_type":"Teich","lat":49.861688826,"lng":8.727499432,"geocode_source":"alleangeln_json_ld","country":"DE","last_updated":"2026-05-07T11:19:14.151Z","source":"alle-angeln","source_platform":"alleangeln","global_id":"alleangeln-ludwigsteich-roßdorf","external_ids":{"alleangeln":"ludwigsteich-roßdorf"}}