{"url":"https://www.alleangeln.de/gewaesser/nagoldtalsperre","slug":"nagoldtalsperre","id":"nagoldtalsperre","name":"Nagoldtalsperre","description":"Nagoldtalsperre ist ein Stausee in Baden-Württemberg in der Nähe von Grömbach. Das Gewässer wird von unseren Mitgliedern sehr stark befischt und als Top Gewässer bewertet.","followers":626,"catches_count":177,"images_count":16,"most_caught_fish":["Flussbarsch","Karpfen","Bachforelle","Rotauge","Schleie","Zander"],"best_method":"Spinnfischen","breadcrumbs":[],"fish":[],"water_type":"Stausee","lat":48.55645869133,"lng":8.4956069365235,"geocode_source":"alleangeln_json_ld","country":"DE","last_updated":"2026-05-07T11:38:46.952Z","source":"alle-angeln","source_platform":"alleangeln","global_id":"alleangeln-nagoldtalsperre","external_ids":{"alleangeln":"nagoldtalsperre"}}