{"id":"alleangeln-kyll-speicher","source_platform":"alleangeln","source_ids":{"alleangeln":"kyll-speicher"},"name":"Kyll (Speicher)","water_type":"Fluss","country":"DE","center":{"lat":49.936627,"lng":6.627154,"source":"alleangeln_json_ld","confidence":"medium"},"geometry":{"points":[{"lat":49.936627,"lng":6.627154}],"lines":[],"polygons":[],"source":"alleangeln_json_ld","confidence":"low"},"links":{"source":"https://www.alleangeln.de/gewaesser/kyll-speicher","hejfish":null,"alleangeln":"https://www.alleangeln.de/gewaesser/kyll-speicher","website":"http://leafletjs.com/","image":null},"fish":["Bachforelle","Hecht","Karpfen"],"metadata":{"platform":"alleangeln","geocode_source":"alleangeln_json_ld","slug":"kyll-speicher","description":"Kyll (Speicher) ist ein Fluss in Rheinland-Pfalz in der Nähe von Speicher. Das Gewässer wird von unseren Mitgliedern relativ wenig befischt und als Top Angelreview bewertet.","followers":81,"catches_count":12,"website":"http://leafletjs.com/","best_method":"Grundangeln","scraper_version":2,"source_last_updated":"2026-05-11T19:03:56.714Z","error":false},"last_updated":"2026-05-11T19:03:56.714Z"}