{"url":"https://www.alleangeln.de/gewaesser/kaisheimer-fischteiche","slug":"kaisheimer-fischteiche","id":"kaisheimer-fischteiche","name":"Kaisheimer Fischteiche","description":"Kaisheimer Fischteiche ist ein See in Bayern in der Nähe von Kaisheim. Das Gewässer wird von unseren Mitgliedern relativ wenig befischt und als Top Angelreview bewertet.","followers":26,"catches_count":18,"images_count":0,"most_caught_fish":["Karpfen","Zander","Aal","Hecht","Regenbogenforelle","Schleie"],"best_method":"Posenfischen","breadcrumbs":[],"fish":[],"water_type":"See","lat":48.769472576792,"lng":10.80501280725,"geocode_source":"alleangeln_json_ld","country":"DE","last_updated":"2026-05-07T10:56:58.993Z","source":"alle-angeln","source_platform":"alleangeln","global_id":"alleangeln-kaisheimer-fischteiche","external_ids":{"alleangeln":"kaisheimer-fischteiche"}}