{"id":"alleangeln-saaler-tongruben","source_platform":"alleangeln","source_ids":{"alleangeln":"saaler-tongruben"},"name":"Saaler Tongruben","water_type":"Baggersee","country":"DE","center":{"lat":54.307175,"lng":12.512044,"source":"alleangeln_json_ld","confidence":"medium"},"geometry":{"points":[{"lat":54.307175,"lng":12.512044}],"lines":[],"polygons":[],"source":"alleangeln_json_ld","confidence":"low"},"links":{"source":"https://www.alleangeln.de/gewaesser/saaler-tongruben","hejfish":null,"alleangeln":"https://www.alleangeln.de/gewaesser/saaler-tongruben","website":"http://www.lav-mv.de/gewaesservz/waters/view/13586","image":null},"fish":["Hecht","Flussbarsch","Aal","Rotauge","Schleie","3 weitere Fischarten","Rotfeder","Karpfen","Güster"],"metadata":{"platform":"alleangeln","geocode_source":"alleangeln_json_ld","slug":"saaler-tongruben","description":"Saaler Tongruben ist ein Baggersee in Mecklenburg-Vorpommern in der Nähe von Saal. Das Gewässer wird von unseren Mitgliedern sehr stark befischt und als gutes Gewässer bewertet.","followers":344,"catches_count":94,"images_count":29,"website":"http://www.lav-mv.de/gewaesservz/waters/view/13586","best_method":"Posenfischen","scraper_version":2,"source_last_updated":"2026-05-11T19:56:25.216Z","error":false},"last_updated":"2026-05-11T19:56:25.216Z"}