{"url":"https://www.alleangeln.de/gewaesser/allermöher-fleet-system","slug":"allermöher-fleet-system","id":"allermöher-fleet-system","name":"Allermöher Fleet-System","description":"Allermöher Fleet-System ist ein Graben in Hamburg. Das Gewässer wird von unseren Mitgliedern sehr stark befischt und als Top Gewässer bewertet.","followers":168,"catches_count":167,"images_count":6,"most_caught_fish":["Hecht","Flussbarsch","Brachse","Aal","Schleie","5 weitere Fischarten"],"best_method":"Spinnfischen","breadcrumbs":[],"fish":[],"water_type":"Graben","lat":53.484039926496,"lng":10.162741573025,"geocode_source":"alleangeln_json_ld","country":"DE","last_updated":"2026-05-07T11:38:14.845Z","source":"alle-angeln","source_platform":"alleangeln","global_id":"alleangeln-allermöher-fleet-system","external_ids":{"alleangeln":"allermöher-fleet-system"}}