{"url":"https://www.alleangeln.de/gewaesser/waldsee-fechenheim","slug":"waldsee-fechenheim","id":"waldsee-fechenheim","name":"Waldsee (Fechenheim)","description":"Waldsee (Fechenheim) ist ein See in Hessen in der Nähe von Frankfurt am Main. Das Gewässer wird von unseren Mitgliedern relativ stark befischt und als Top Gewässer bewertet.","followers":120,"catches_count":42,"images_count":1,"most_caught_fish":["Karpfen","Hecht","Schleie","Wels","Zander","Flussbarsch"],"best_method":"Grundangeln","breadcrumbs":[],"fish":[],"water_type":"See","lat":50.141466575502,"lng":8.7790163313032,"geocode_source":"alleangeln_json_ld","country":"DE","last_updated":"2026-05-07T11:16:40.478Z","source":"alle-angeln","source_platform":"alleangeln","global_id":"alleangeln-waldsee-fechenheim","external_ids":{"alleangeln":"waldsee-fechenheim"}}