{"id":"alleangeln-havøysundet","source_platform":"alleangeln","source_ids":{"alleangeln":"havøysundet"},"name":"Havøysundet","water_type":"Meer","country":"DE","center":{"lat":70.994279,"lng":24.639951,"source":"alleangeln_json_ld","confidence":"medium"},"geometry":{"points":[{"lat":70.994279,"lng":24.639951}],"lines":[],"polygons":[],"source":"alleangeln_json_ld","confidence":"low"},"links":{"source":"https://www.alleangeln.de/gewaesser/havøysundet","hejfish":null,"alleangeln":"https://www.alleangeln.de/gewaesser/havøysundet","image":null},"fish":["Heilbutt","Dorsch","Köhler","Sonstiges","Seeskorpion","Makrele","Rotbarsch","Seewolf"],"metadata":{"platform":"alleangeln","geocode_source":"alleangeln_json_ld","slug":"havøysundet","description":"Havøysundet ist ein Meer in Norwegen. Das Gewässer wird von unseren Mitgliedern relativ stark befischt und als Top Gewässer bewertet.","followers":42,"catches_count":39,"images_count":1,"best_method":"Meeresangeln (auf See)","source_last_updated":"2026-05-07T11:15:25.489Z","error":false},"last_updated":"2026-05-07T11:15:25.489Z"}