{"url":"https://www.alleangeln.de/gewaesser/jachthafen-wesel","slug":"jachthafen-wesel","id":"jachthafen-wesel","name":"Jachthafen Wesel","description":"Jachthafen Wesel ist ein Hafen in Nordrhein-Westfalen in der Nähe von Wesel. Das Gewässer wird von unseren Mitgliedern sehr stark befischt und als Top Gewässer bewertet.","followers":253,"catches_count":64,"images_count":1,"most_caught_fish":["Zander","Brachse","Rotauge","Flussbarsch","Aal","Rapfen","Aland","Karpfen"],"best_method":"Grundangeln","breadcrumbs":[],"fish":[],"water_type":"Hafen","lat":51.662626181018,"lng":6.5837227989502,"geocode_source":"alleangeln_json_ld","country":"DE","last_updated":"2026-05-07T11:25:04.960Z","source":"alle-angeln","source_platform":"alleangeln","global_id":"alleangeln-jachthafen-wesel","external_ids":{"alleangeln":"jachthafen-wesel"}}