{"url":"https://www.alleangeln.de/gewaesser/plageteich-witzeeze","slug":"plageteich-witzeeze","id":"plageteich-witzeeze","name":"Plageteich (Witzeeze)","description":"Plageteich (Witzeeze) ist ein Teich in Schleswig-Holstein in der Nähe von Witzeeze. Das Gewässer wird von unseren Mitgliedern sehr wenig befischt und als Top Gewässer bewertet.","followers":56,"catches_count":7,"images_count":0,"most_caught_fish":["Wels","Hecht"],"best_method":"Posenfischen","breadcrumbs":[],"fish":[],"water_type":"Teich","lat":53.461308884845,"lng":10.634136288672,"geocode_source":"alleangeln_json_ld","country":"DE","last_updated":"2026-05-07T10:14:42.976Z","source":"alle-angeln","source_platform":"merged","global_id":"alleangeln-plageteich-witzeeze","external_ids":{"alleangeln":"plageteich-witzeeze"}}