{"url":"https://www.alleangeln.de/gewaesser/marmara","slug":"marmara","id":"marmara","name":"Marmarameer (Marmara)","description":"Marmarameer (Marmara) ist ein Meer in Türkei. Das Gewässer wird von unseren Mitgliedern sehr wenig befischt und als Top Gewässer bewertet.","followers":5,"catches_count":8,"images_count":0,"most_caught_fish":["Sonstiges"],"best_method":"Meeresangeln (Küste)","breadcrumbs":[],"fish":[],"water_type":"Meer","lat":40.584736837104,"lng":27.556348800659,"geocode_source":"alleangeln_json_ld","country":"DE","last_updated":"2026-05-07T10:20:36.218Z","source":"alle-angeln","source_platform":"merged","global_id":"alleangeln-marmara","external_ids":{"alleangeln":"marmara"}}