{"url":"https://www.alleangeln.de/gewaesser/canal-du-rhône-au-rhin-bourogne","slug":"canal-du-rhône-au-rhin-bourogne","id":"canal-du-rhône-au-rhin-bourogne","name":"Canal du Rhône au Rhin (Bourogne)","description":"Canal du Rhône au Rhin (Bourogne) ist ein Kanal in Frankreich. Das Gewässer wird von unseren Mitgliedern sehr wenig befischt und als gutes Gewässer bewertet.","followers":32,"catches_count":9,"images_count":0,"most_caught_fish":["Brachse","Karausche","Sonnenbarsch"],"best_method":"Feedern","breadcrumbs":[],"fish":[],"water_type":"Kanal","lat":47.556591292953,"lng":6.9241895675659,"geocode_source":"alleangeln_json_ld","country":"DE","last_updated":"2026-05-07T10:22:23.662Z","source":"alle-angeln","source_platform":"merged","global_id":"alleangeln-canal-du-rhône-au-rhin-bourogne","external_ids":{"alleangeln":"canal-du-rhône-au-rhin-bourogne"}}