{"id":"hejfish-15336","source_platform":"merged","source_ids":{"hejfish":15336,"alleangeln":"tagebausee-wölfersheim"},"name":"Tagebausee Wölfersheim (Gästebegleitkarten)","water_type":"Baggersee","country":"DE","center":{"lat":50.400281,"lng":8.8377,"source":"hejfish_api_map","confidence":"high"},"geometry":{"points":[{"lat":50.400281,"lng":8.8377}],"lines":[],"polygons":[],"source":"hejfish_api_map","confidence":"medium"},"links":{"source":"https://www.hejfish.com/d/15336-tagebausee-woelfersheim-gaestebegleitkarten","hejfish":"https://www.hejfish.com/d/15336-tagebausee-woelfersheim-gaestebegleitkarten","alleangeln":"https://www.alleangeln.de/gewaesser/tagebausee-wölfersheim","website":"http://www.asv-woelfersheim.de/","image":"https://file.hejfish.com/image/cc1200x900/7d/b8/7db87a9de7c1abc3765c9941d5beded42de9908f.jpg"},"fish":["Aal","Hecht","Wildkarpfen","Rotfeder","Schleie","Zander","Gründling","Karausche","Stör","Flussbarsch","Wels","Karpfen","Döbel","Rotauge","Brasse","Regenbogenforelle","Giebel","5 weitere Fischarten"],"metadata":{"merged_fields":{"center":"hejfish","fish":["hejfish","alleangeln"],"description":"hejfish","geometry":"hejfish","water_type":"hejfish"},"sources":{"hejfish":{"platform":"hejfish","geocode_source":"hejfish_api_map","slug":"tagebausee-woelfersheim-gaestebegleitkarten","seo_name":"Tagebausee Wölfersheim (Gästebegleitkarten)","description":"<p>Der Wölfersheimer See liegt östlich von der Gemeinde Wölfersheim im hessischen Landkreis Wetteraukreis. Es handelt sich dabei um einen Tagebau-Restsee, der heute vorwiegend als Angelrevier und zur Naherholung genutzt werden. An schönen auch teilweise flachen Uferstellen ist das Angeln sehr gut möglich.</p>","techniques":["Karpfenangeln","Feedern","Friedfischangeln","Naturköderangeln","Posenangeln","Raubfischangeln","Spinnangeln","Stippangeln"],"manager":{"id":2002,"name":"Angelsportverein Wölfersheim und Umgebung e.V.","street":"Geisenheimer Str. 25","postal_code":"61200","city":"Wölfersheim","telephone":"","email":"info@asv-woelfersheim.de","website":"https://www.asv-woelfersheim.de","logo":"https://file.hejfish.com/image/r200x200/67/4c/674c2db460e524ecc795b7cefa730dd0c4cf69b4.png","slug":"angelsportverein-woelfersheim-und-umgebung-e-v"},"season_begin":"0001-01-01","season_end":"0001-12-15","features":{"accessible":false,"public_transport":false,"boat":false,"belly_boat":false,"digital_ticket":true,"night_fishing":true,"ice_fishing":false,"depth_map":true,"has_gauges":false},"location":{"city":{"id":15749,"name":"Reichelsheim (Wetterau)"},"district":{"id":222,"name":"Wetteraukreis"},"state":{"id":14,"name":"Hessen","slug":"hessen"},"country":{"id":2,"name":"Deutschland","code":"de","slug":"deutschland"}},"source_last_updated":"2026-05-07T11:45:35.461Z","error":false},"alleangeln":{"platform":"alleangeln","geocode_source":"alleangeln_json_ld","slug":"tagebausee-wölfersheim","description":"Tagebausee Wölfersheim ist ein See in Hessen in der Nähe von Wölfersheim. Das Gewässer wird von unseren Mitgliedern sehr stark befischt und als Top Gewässer bewertet.","followers":446,"catches_count":64,"images_count":4,"website":"http://www.asv-woelfersheim.de/","best_method":"Grundangeln","scraper_version":2,"source_last_updated":"2026-05-11T19:49:35.253Z","error":false}}},"last_updated":"2026-05-11T19:49:35.253Z"}