{"id":15083,"slug":"scheyern","url":"https://www.hejfish.com/d/15083-scheyern","name":"Scheyern","description":"","water_size_ha":null,"fish":["ZanderHechtFlussbarschKarpfenAalBrasseRotaugeRotfederGiebelSchleie"],"techniques":["AnsitzangelnFeedern… mehr"],"properties":["kein Boot\nNachtfischenFangmeldung erforderlich\nTechniken:\nAnsitzangelnFeedern… mehr"],"season":null,"water_type":null,"rules_text":"","mobile_ticket":false,"print_required":false,"tickets":[],"manager":null,"main_image":null,"location_info":["Bayern","Kreis Neuburg-Schrobenhausen"],"lat":null,"lng":null,"geocode_source":null,"map_data":{"data":{"id":15083,"geojson":{"type":"FeatureCollection","features":[{"type":"Feature","properties":{"name":"Parkplatz","marker-color":"#1b17de","marker-size":"medium"},"geometry":{"coordinates":[11.447492164227185,48.501438806472805],"type":"Point"}}]},"locations":[{"lat":48.50189,"lng":11.4432}],"stations":[],"gauges":[],"depth_map":null}},"country":"DE","last_updated":"2026-05-05T21:14:41.070Z","error":false}