{"id":15720,"slug":"haidenaab-2-fv-fuerth","url":"https://www.hejfish.com/d/15720-haidenaab-2-fv-fuerth","name":"Haidenaab 2 (FV Fürth)","description":"","water_size_ha":null,"fish":["Forelle"],"techniques":["AnsitzangelnFriedfischangeln… mehr"],"properties":["kein Boot\nKein Nachtfischen\nTechniken:\nAnsitzangelnFriedfischangeln… mehr"],"season":null,"water_type":null,"rules_text":"","mobile_ticket":false,"print_required":false,"tickets":[],"manager":null,"main_image":null,"location_info":["Bayern","Kreis Neustadt an der Waldnaab"],"lat":null,"lng":null,"geocode_source":null,"map_data":{"data":{"id":15720,"geojson":[],"locations":[{"lat":49.75506,"lng":11.93987},{"lat":49.74521,"lng":11.958}],"stations":[{"name":"Pressath","lat":49.764072,"lng":11.939149,"lines":null,"url":null},{"name":"Pressath, Schinnerstr.","lat":49.763346,"lng":11.944323,"lines":null,"url":null},{"name":"Troschelhammer","lat":49.743665,"lng":11.965551,"lines":null,"url":null}],"gauges":[{"id":1428,"name":"Unterbruck Flutmulde","lat":49.8230841,"lng":11.8912071},{"id":1430,"name":"Wildenau","lat":49.608343,"lng":12.1282828},{"id":1429,"name":"Pressath","lat":49.7678833,"lng":11.9316165},{"id":1427,"name":"Unterbruck","lat":49.8234292,"lng":11.8921593}],"depth_map":null}},"country":"DE","last_updated":"2026-05-05T21:33:15.770Z","error":false}