{"id":"hejfish-13699","source_platform":"hejfish","source_ids":{"hejfish":13699},"name":"Sülzpfuhl bei Rühn","water_type":"See","country":"DE","center":{"lat":53.824139,"lng":11.935333,"source":"hejfish_api_map_geojson","confidence":"high"},"geometry":{"points":[{"lat":53.824139,"lng":11.935333},{"lat":53.8241,"lng":11.9353}],"lines":[],"polygons":[],"source":"hejfish_api_map_geojson","confidence":"medium"},"links":{"source":"https://www.hejfish.com/d/13699-suelzpfuhl-bei-ruehn","hejfish":"https://www.hejfish.com/d/13699-suelzpfuhl-bei-ruehn","alleangeln":null,"image":null},"fish":["Hecht","Karpfen","Schleie","Flussbarsch","Rotauge","Aal","Karausche"],"metadata":{"platform":"hejfish","geocode_source":"hejfish_api_map_geojson","slug":"suelzpfuhl-bei-ruehn","seo_name":"Sülzpfuhl bei Rühn","techniques":["Spinnangeln","Fliegenfischen","Ansitzangeln","Feedern","Stippangeln","Posenangeln","Oberflächenangeln","Raubfischangeln","Friedfischangeln","Karpfenangeln"],"rules_files":[{"id":292533,"name":"satellitenbild","description":null,"file":"https://api.hejfish.com/files/download/fb3580b5153452ad270aef42cc8e267e22437d08/satellitenbild.pdf"},{"id":292534,"name":"tiefenkarte","description":null,"file":"https://api.hejfish.com/files/download/093371c0097d59c7efe9c65fcc4609de3567eaa7/tiefenkarte.pdf"},{"id":884564,"name":"Gewaesserordnung 01.01.2023","description":null,"file":"https://api.hejfish.com/files/download/d4cbab17110d09a2062535e73af3194f406fe45b/Gewaesserordnung%2001.01.2023.pdf"}],"tickets":[{"name":"Tageskarte - Erwachsene","price":"16,00 EUR","ticket_type_id":4826,"price_id":97815},{"name":"Tageskarte - Jugend","price":"4,00 EUR","ticket_type_id":4826,"price_id":97816},{"name":"2-Tageskarte - Erwachsene","price":"32,00 EUR","ticket_type_id":4827,"price_id":97817},{"name":"2-Tageskarte - Jugend","price":"8,00 EUR","ticket_type_id":4827,"price_id":97818},{"name":"Wochenkarte - Erwachsene","price":"92,00 EUR","ticket_type_id":4828,"price_id":97819},{"name":"Wochenkarte - Jugend","price":"20,00 EUR","ticket_type_id":4828,"price_id":97820},{"name":"Monatskarte - Erwachsene","price":"172,00 EUR","ticket_type_id":4829,"price_id":97821}],"manager":{"id":1834,"name":"Landesanglerverband Mecklenburg-Vorpommern e.V.","street":"OT Görslow, Siedlung 18a","postal_code":"19067","city":"Leezen","telephone":"","email":"","website":"https://www.lav-mv.de/","logo":"https://file.hejfish.com/image/r200x200/37/cb/37cb2792d40e6c06eadde2bd767e4c1c68624403.png","slug":"landesanglerverband-mecklenburg-vorpommern-e-v"},"season_begin":"0001-01-01","season_end":"0001-12-31","features":{"accessible":false,"public_transport":true,"boat":true,"belly_boat":true,"digital_ticket":true,"night_fishing":true,"ice_fishing":false,"depth_map":false,"has_gauges":false},"location":{"city":{"id":8807,"name":"Rühn"},"district":{"id":148,"name":"Kreis Rostock"},"state":{"id":20,"name":"Mecklenburg-Vorpommern","slug":"mecklenburg-vorpommern"},"country":{"id":2,"name":"Deutschland","code":"de","slug":"deutschland"}},"source_last_updated":"2026-05-07T11:43:08.447Z","error":false},"last_updated":"2026-05-07T11:43:08.447Z"}